PrintWithPager/__init__.py
PrintWithPager/pager.py
PyPager/__init__.py
PyPager/pager.py
pager/__init__.py
pager/pager.py
PrintWithPager-1.0.0.dist-info/LICENSE.txt
PrintWithPager-1.0.0.dist-info/METADATA
PrintWithPager-1.0.0.dist-info/WHEEL
PrintWithPager-1.0.0.dist-info/top_level.txt
PrintWithPager-1.0.0.dist-info/RECORD
