Metadata-Version: 2.1
Name: PrintWithPager
Version: 1.0.0
Summary: Simple pager package to helpwith printing output using a pager
Home-page: https://github.com/NAndLib/pager
Author: Andrew Tran
Author-email: andremail03@gmail.com
License: MIT
Keywords: pager printer less python
Platform: UNKNOWN
Requires-Python: >3
